LICENSE
MANIFEST.in
README.md
README.rst
requirements.txt
setup.py
pdml2flow/__init__.py
pdml2flow/autovivification.py
pdml2flow/cli.py
pdml2flow/conf.py
pdml2flow/flow.py
pdml2flow/logging.py
pdml2flow/pdmlhandler.py
pdml2flow/plugin.py
pdml2flow/utils.py
pdml2flow.egg-info/PKG-INFO
pdml2flow.egg-info/SOURCES.txt
pdml2flow.egg-info/dependency_links.txt
pdml2flow.egg-info/entry_points.txt
pdml2flow.egg-info/requires.txt
pdml2flow.egg-info/top_level.txt
pdml2flow/plugin-skeleton/.gitignore
pdml2flow/plugin-skeleton/.travis.yml
pdml2flow/plugin-skeleton/LICENSE
pdml2flow/plugin-skeleton/MANIFEST.in
pdml2flow/plugin-skeleton/README.md
pdml2flow/plugin-skeleton/requirements.txt
pdml2flow/plugin-skeleton/setup.py
pdml2flow/plugin-skeleton/plugin/__init__.py
pdml2flow/plugin-skeleton/plugin/plugin.py
pdml2flow/plugin-skeleton/scripts/mkreadme.sh
pdml2flow/plugins/__init__.py
pdml2flow/plugins/json_output.py
pdml2flow/plugins/xml_output.py
test/test_autovivification.py
test/test_cli.py
test/test_conf.py
test/test_flow.py
test/test_logging.py
test/test_plugin.py
test/test_system.py
test/test_utils.py
test/testcase.py