Metadata-Version: 1.0
Name: pdml2flow
Version: 5.3
Summary: Aggregates wireshark pdml to flows
Home-page: https://github.com/Enteee/pdml2flow
Author: Mischa Lehmann
Author-email: ducksource@duckpond.ch
License: Apache 2.0
Keywords: wireshark pdml flow aggregation plugins
Platform: UNKNOWN
